st_signedUrl_uploader/__init__.py
st_signedUrl_uploader/frontend/build/asset-manifest.json
st_signedUrl_uploader/frontend/build/bootstrap.min.css
st_signedUrl_uploader/frontend/build/index.html
st_signedUrl_uploader/frontend/build/static/js/main.022a2283.js
st_signedUrl_uploader/frontend/build/static/js/main.022a2283.js.LICENSE.txt
st_signedUrl_uploader/frontend/build/static/js/main.022a2283.js.map
st_signedUrl_uploader/frontend/build/static/js/main.171a7522.js
st_signedUrl_uploader/frontend/build/static/js/main.171a7522.js.LICENSE.txt
st_signedUrl_uploader/frontend/build/static/js/main.171a7522.js.map
st_signedUrl_uploader/frontend/build/static/js/main.88223560.js
st_signedUrl_uploader/frontend/build/static/js/main.88223560.js.LICENSE.txt
st_signedUrl_uploader/frontend/build/static/js/main.88223560.js.map
st_signedUrl_uploader-1.3.0.dist-info/LICENSE
st_signedUrl_uploader-1.3.0.dist-info/METADATA
st_signedUrl_uploader-1.3.0.dist-info/WHEEL
st_signedUrl_uploader-1.3.0.dist-info/top_level.txt
st_signedUrl_uploader-1.3.0.dist-info/RECORD
